s3pip/__init__.py
s3pip/s3pip.py
s3pip-0.1.1.data/scripts/s3pip
s3pip-0.1.1.dist-info/DESCRIPTION.rst
s3pip-0.1.1.dist-info/entry_points.txt
s3pip-0.1.1.dist-info/METADATA
s3pip-0.1.1.dist-info/pydist.json
s3pip-0.1.1.dist-info/RECORD
s3pip-0.1.1.dist-info/top_level.txt
s3pip-0.1.1.dist-info/WHEEL
