Metadata-Version: 2.0
Name: s3pip
Version: 0.1.1
Summary: A pip wrapper that uses AWS S3 for package data
Home-page: http://jlafon.io
Author: Jharrod LaFon
Author-email: jlafon@eyesopen.com
License: MIT
Platform: UNKNOWN
Classifier: Development Status :: 3 - Alpha
Classifier: Topic :: Software Development :: Build Tools
Classifier: License :: OSI Approved :: MIT License
Classifier: Intended Audience :: Developers
Classifier: Programming Language :: Python :: 2
Classifier: Programming Language :: Python :: 2.7
Requires-Dist: boto
Requires-Dist: pip (>=1.5)
